omplpy.cpython-38-aarch64-linux-gnu.so
kompass_cpp.cpython-38-aarch64-linux-gnu.so
kompass_core/motion_cost.py
kompass_core/calibration.py
kompass_core/models.py
kompass_core/simulation.py
kompass_core/__init__.py
kompass_core/performance.py
kompass_core/utils/base_attrs.py
kompass_core/utils/base_validators.py
kompass_core/utils/visualization.py
kompass_core/utils/geometry.py
kompass_core/utils/__init__.py
kompass_core/utils/emergency_stop.py
kompass_core/utils/common.py
kompass_core/py_path_tools/__init__.py
kompass_core/py_path_tools/interpolation.py
kompass_core/py_path_tools/executor.py
kompass_core/mapping/__init__.py
kompass_core/mapping/local_mapper.py
kompass_core/algorithms/dvz.py
kompass_core/algorithms/__init__.py
kompass_core/third_party/__init__.py
kompass_core/third_party/ompl/planner.py
kompass_core/third_party/ompl/__init__.py
kompass_core/third_party/ompl/config.py
kompass_core/control/dvz.py
kompass_core/control/rgbd_follower.py
kompass_core/control/pure_pursuit.py
kompass_core/control/dwa.py
kompass_core/control/stanley.py
kompass_core/control/_trajectory_.py
kompass_core/control/__init__.py
kompass_core/control/rgb_follower.py
kompass_core/control/_base_.py
kompass_core/datatypes/path.py
kompass_core/datatypes/pointcloud.py
kompass_core/datatypes/__init__.py
kompass_core/datatypes/obstacles.py
kompass_core/datatypes/scan_model.py
kompass_core/datatypes/laserscan.py
kompass_core/datatypes/pose.py
lib/libkompass.a
kompass_core-0.7.0.dist-info/WHEEL
kompass_core-0.7.0.dist-info/METADATA
kompass_core-0.7.0.dist-info/RECORD
kompass_core-0.7.0.dist-info/licenses/LICENSE
