Metadata-Version: 2.1
Name: kompass_core
Version: 0.7.0
Summary: Navigation Algorithms Library for Kompass
Keywords: robotics,gpgpu,navigation,control,planning,mapping
Author-Email: Automatika Robotics <contact@automatikarobotics.com>
License: MIT
Classifier: License :: OSI Approved :: MIT License
Classifier: Programming Language :: Python :: 3
Classifier: Programming Language :: Python :: 3.8
Classifier: Programming Language :: Python :: 3.10
Classifier: Programming Language :: Python :: 3.11
Classifier: Programming Language :: Python :: 3.12
Project-URL: Homepage, https://github.com/automatika-robotics/kompass-core
Requires-Python: <3.13,>=3.8.4
Requires-Dist: numpy
Requires-Dist: toml
Requires-Dist: attrs>=23.2.0
Requires-Dist: pyyaml
Provides-Extra: dev
Requires-Dist: pip-tools; extra == "dev"
Requires-Dist: pytest==8.0.0; extra == "dev"
Requires-Dist: pre-commit; extra == "dev"
Requires-Dist: opencv-python; extra == "dev"
Requires-Dist: matplotlib; extra == "dev"
